opencce/__init__.py
opencce/utils.py
opencce/x509.py
opencce/__main__.py
opencce/cli.py
opencce/containers/__init__.py
opencce/containers/CCEContainer.py
opencce-0.2.dist-info/entry_points.txt
opencce-0.2.dist-info/metadata.json
opencce-0.2.dist-info/DESCRIPTION.rst
opencce-0.2.dist-info/top_level.txt
opencce-0.2.dist-info/RECORD
opencce-0.2.dist-info/WHEEL
opencce-0.2.dist-info/zip-safe
opencce-0.2.dist-info/METADATA
