Metadata-Version: 2.0
Name: opencce
Version: 0.2
Summary: This is a free software implementation of the CCE (Citizen Card Encrypted) functionality.
Home-page: https://github.com/privatwolke/opencce
Author: Stephan Klein
Author-email: UNKNOWN
License: MIT
Keywords: encryption citizencard CCE
Platform: UNKNOWN
Classifier: Development Status :: 4 - Beta
Classifier: Environment :: Console
Classifier: Intended Audience :: Information Technology
Classifier: License :: OSI Approved :: MIT License
Classifier: Natural Language :: English
Classifier: Operating System :: POSIX
Classifier: Programming Language :: Python :: 2.7
Classifier: Topic :: Utilities
Requires-Dist: lxml
Requires-Dist: M2Crypto
Requires-Dist: python-magic
